{"title":"SM Entertainment ─ RECRUIT","url":"https://recruit.smentertainment.com/","favicon":"https://recruit.smentertainment.com/favicon.ico","elements":[{"title":"SM브랜드마케팅 콘텐츠 디자인 담당 채용 (수시채용)","contents":"2023-03-23 ~ 2023-12-31","link":"https://recruit.smentertainment.com/Employ?employNo=1017","retrieved":1679980221548},{"title":"SM컬처앤콘텐츠 연기자매니지먼트 매니저 모집(신입/경력)","contents":"2023-09-21 ~ 2023-10-20","link":"https://recruit.smentertainment.com/Employ?employNo=1177","retrieved":1695280191036},{"title":"SM컬처앤콘텐츠 여행사업 항공예약발권(T/D) 담당 경력직 모집","contents":"2023-09-21 ~ 2023-10-03","link":"https://recruit.smentertainment.com/Employ?employNo=1176","retrieved":1695265799600},{"title":"SM컬처앤콘텐츠 광고기획(AE) 경력직 모집","contents":"2023-09-19 ~ 2023-10-03","link":"https://recruit.smentertainment.com/Employ?employNo=1175","retrieved":1695104009572},{"title":"SM컬처앤콘텐츠 여행사업 항공예약발권 담당 모집(신입/경력)","contents":"2023-09-12 ~ 2023-10-03","link":"https://recruit.smentertainment.com/Employ?employNo=1172","retrieved":1694488197014},{"title":"SM컬처앤콘텐츠 인사/HR 담당(신입) 모집","contents":"2023-09-11 ~ 2023-09-21","link":"https://recruit.smentertainment.com/Employ?employNo=1171","retrieved":1694419985733},{"title":"SM엔터테인먼트 디자인 인턴 채용","contents":"2023-09-08 ~ 2023-09-21","link":"https://recruit.smentertainment.com/Employ?employNo=1170","retrieved":1694354860963},{"title":"SM엔터테인먼트 디자인 담당자 채용","contents":"2023-09-08 ~ 2023-09-21","link":"https://recruit.smentertainment.com/Employ?employNo=1169","retrieved":1694354860968},{"title":"SM엔터테인먼트 MD 국내 유통 담당자 채용","contents":"2023-09-08 ~ 2023-09-21","link":"https://recruit.smentertainment.com/Employ?employNo=1168","retrieved":1694527767819},{"title":"SM엔터테인먼트 MD 기획 담당자 채용","contents":"2023-09-08 ~ 2023-09-21","link":"https://recruit.smentertainment.com/Employ?employNo=1167","retrieved":1694786942397}]}